{
  "columns":
  ["", "ALUTs", "FFs", "RAMs", "DSPs", "MLABs", "Details"]
  , "debug_enabled":"true"
  , "type":"module"
  , "total_percent":
  [19.1061, 12.0012, 8.18275, 5.44747, 18.75]
  , "total":
  [6270, 17932, 28, 21, 344]
  , "name":"System"
  , "max_resources":
  [109572, 219144, 514, 112, 5478]
  , "children":
  [
    {
      "name":"myproject"
      , "compute_units":1
      , "type":"function"
      , "total_percent":
      [19.1061, 12.0012, 8.18275, 5.44747, 18.75]
      , "total_kernel_resources":
      [6270, 17932, 28, 21, 344]
      , "details":
      [
        {
          "type":"text"
          , "text":"Number of compute units: 1"
        }
        , {
          "type":"brief"
          , "text":"1 compute unit."
        }
      ]
      , "children":
      [
        {
          "name":"Coalesced Variables: \n - 'layer6_out' (myproject.cpp:68)\n - 'acc' (nnet_dense.h:114)\n - 'datareg' (nnet_activation.h:29)"
          , "type":"resource"
          , "data":
          [110, 540, 0, 0, 0]
          , "debug":
          [
            [
              {
                "filename":"firmware/myproject.cpp"
                , "line":68
              }
            ]
            , [
              {
                "filename":"firmware/nnet_utils/nnet_activation.h"
                , "line":29
              }
            ]
            , [
              {
                "filename":"firmware/nnet_utils/nnet_dense.h"
                , "line":114
              }
            ]
          ]
          , "details":
          [
            {
              "type":"text"
              , "text":"Type: Register"
            }
            , {
              "type":"text"
              , "text":"10 registers of width 24 bits and depth 2"
              , "details":
              [
                {
                  "type":"text"
                  , "text":" Depth was increased by a factor of 2 due to a loop initiation interval of 2."
                }
              ]
            }
            , {
              "type":"brief"
              , "text":"Register,\n10 regs, 24 width by 2 depth"
            }
          ]
        }
        , {
          "name":"Coalesced Variables: \n - 'w_index' (nnet_dense.h:128)\n - 'in_index' (nnet_dense.h:127)\n - 'ir' (nnet_dense.h:123)"
          , "type":"resource"
          , "data":
          [11, 18, 0, 0, 0]
          , "debug":
          [
            [
              {
                "filename":"firmware/nnet_utils/nnet_dense.h"
                , "line":123
              }
            ]
            , [
              {
                "filename":"firmware/nnet_utils/nnet_dense.h"
                , "line":127
              }
            ]
            , [
              {
                "filename":"firmware/nnet_utils/nnet_dense.h"
                , "line":128
              }
            ]
          ]
          , "details":
          [
            {
              "type":"text"
              , "text":"Type: Register"
            }
            , {
              "type":"text"
              , "text":"1 register of width 6 bits and depth 2"
              , "details":
              [
                {
                  "type":"text"
                  , "text":" Depth was increased by a factor of 2 due to a loop initiation interval of 2."
                }
              ]
            }
            , {
              "type":"brief"
              , "text":"Register,\n1 reg, 6 width by 2 depth"
            }
          ]
        }
        , {
          "name":"Component call"
          , "type":"resource"
          , "data":
          [0, 0, 0, 0, 0]
          , "details":
          [
            {
              "type":"text"
              , "text":"Stream implemented 3136 bits wide with a buffer size of 0 elements."
            }
            , {
              "type":"brief"
              , "text":"3136b wide with 0 elements."
            }
          ]
        }
        , {
          "name":"Component return"
          , "type":"resource"
          , "data":
          [0, 0, 0, 0, 0]
          , "details":
          [
            {
              "type":"text"
              , "text":"Stream implemented 160 bits wide with a buffer size of 0 elements."
            }
            , {
              "type":"brief"
              , "text":"160b wide with 0 elements."
            }
          ]
        }
        , {
          "name":"Variable: \n - 'ir' (nnet_dense.h:123)"
          , "type":"resource"
          , "data":
          [11, 70, 0, 0, 0]
          , "debug":
          [
            [
              {
                "filename":"firmware/nnet_utils/nnet_dense.h"
                , "line":123
              }
            ]
          ]
          , "details":
          [
            {
              "type":"text"
              , "text":"Type: Register"
            }
            , {
              "type":"text"
              , "text":"1 register of width 32 bits and depth 2"
              , "details":
              [
                {
                  "type":"text"
                  , "text":" Depth was increased by a factor of 2 due to a loop initiation interval of 2."
                }
              ]
            }
            , {
              "type":"brief"
              , "text":"Register,\n1 reg, 32 width by 2 depth"
            }
          ]
        }
        , {
          "name":"myproject.cpp:47 (inputs.input_2)"
          , "type":"resource"
          , "data":
          [0, 0, 0, 0, 256]
          , "debug":
          [
            [
              {
                "filename":"firmware/myproject.cpp"
                , "line":47
              }
            ]
          ]
          , "details":
          [
            {
              "type":"table"
              , "Memory system":"Stall-free"
              , "Requested size":"392 bytes"
              , "Implemented size":"512 bytes"
              , "Memory Usage":"256 MLABs"
              , "Number of banks":"1"
              , "Bank width":"4096 bits"
              , "Bank depth":"1 word"
              , "Number of replicates":"1"
              , "Number of private copies":"1"
              , "Additional information":"Requested size 392 bytes, implemented size 512 bytes, stall-free, 1 read and 1 write. "
            }
            , {
              "type":"brief"
              , "text":"Stall-free,\n392B requested,\n512B implemented."
            }
          ]
        }
        , {
          "name":"w3.h:15 (w3)"
          , "type":"resource"
          , "data":
          [0, 0, 16, 0, 0]
          , "debug":
          [
            [
              {
                "filename":"firmware/weights/w3.h"
                , "line":15
              }
            ]
          ]
          , "details":
          [
            {
              "type":"table"
              , "Memory system":"Stall-free"
              , "Requested size":"16384 bytes"
              , "Implemented size":"16384 bytes"
              , "Memory Usage":""
              , "Number of banks":"16 (banked on bits 10, 11, 12, 13)"
              , "Bank width":"16 bits"
              , "Bank depth":"512 words"
              , "Number of replicates":"1"
              , "Number of private copies":"1"
              , "User defined HLS attributes":"hls_memory_impl(BLOCK_RAM); hls_bankwidth: 2; hls_numbanks: 16; "
              , "Additional information":
              [
                {
                  "type":"text"
                  , "text":"Requested size 16384 bytes, implemented size 16384 bytes, stall-free, 32 reads and 0 writes. "
                }
                , {
                  "type":"text"
                  , "text":"Banked on bits 10, 11, 12, 13 into 16 separate banks."
                }
                , {
                  "type":"text"
                  , "text":"Reducing accesses to exactly one read and one write for all on-chip memory systems may increase overall system performance."
                }
              ]
            }
            , {
              "type":"brief"
              , "text":"Stall-free,\n16384B requested,\n16384B implemented."
            }
          ]
        }
        , {
          "name":"myproject.B1.start"
          , "type":"basicblock"
          , "children":
          [
            {
              "name":"State"
              , "type":"resource"
              , "data":
              [194, 3528, 0, 0, 0]
              , "details":
              [
                {
                  "type":"brief"
                  , "text":"Live values and control logic"
                }
                , {
                  "type":"text"
                  , "text":"Resources for live values and control logic. To reduce this area:"
                  , "details":
                  [
                    {
                      "type":"text"
                      , "text":"reduce size of local variables"
                    }
                    , {
                      "type":"text"
                      , "text":"reduce scope of local variables, localizing them as much as possible"
                    }
                    , {
                      "type":"text"
                      , "text":"reduce number of nested loops"
                    }
                  ]
                }
              ]
              , "children":
              [
                {
                  "name":"No Source Line"
                  , "type":"resource"
                  , "data":
                  [194, 3528, 0, 0, 0]
                }
              ]
            }
            , {
              "name":"Feedback"
              , "type":"resource"
              , "data":
              [79, 62, 1, 0, 0]
              , "details":
              [
                {
                  "type":"brief"
                  , "text":"Loop-carried dependencies"
                }
                , {
                  "type":"text"
                  , "text":"Resources for loop-carried dependencies. To reduce this area:"
                  , "details":
                  [
                    {
                      "type":"text"
                      , "text":"reduce number and size of loop-carried variables"
                    }
                  ]
                }
              ]
              , "children":
              [
                {
                  "name":"myproject.cpp:63 > nnet_dense.h:163 > \nnnet_dense.h:114"
                  , "type":"resource"
                  , "data":
                  [72, 60, 1, 0, 0]
                  , "debug":
                  [
                    [
                      {
                        "filename":"/home/renz/hls4ml_14/firmware/myproject.cpp"
                        , "line":63
                      }
                      , {
                        "filename":"/home/renz/hls4ml_14/firmware/nnet_utils/nnet_dense.h"
                        , "line":163
                      }
                      , {
                        "filename":"/home/renz/hls4ml_14/firmware/nnet_utils/nnet_dense.h"
                        , "line":114
                      }
                    ]
                  ]
                }
                , {
                  "name":"myproject.cpp:63 > nnet_dense.h:163 > \nnnet_dense.h:133 > ac_fixed.h:300"
                  , "type":"resource"
                  , "data":
                  [7, 2, 0, 0, 0]
                  , "debug":
                  [
                    [
                      {
                        "filename":"/home/renz/hls4ml_14/firmware/myproject.cpp"
                        , "line":63
                      }
                      , {
                        "filename":"/home/renz/hls4ml_14/firmware/nnet_utils/nnet_dense.h"
                        , "line":163
                      }
                      , {
                        "filename":"/home/renz/hls4ml_14/firmware/nnet_utils/nnet_dense.h"
                        , "line":133
                      }
                    ]
                  ]
                }
              ]
            }
            , {
              "name":"Cluster logic"
              , "type":"resource"
              , "data":
              [9, 6, 0, 0, 1]
              , "details":
              [
                {
                  "type":"brief"
                  , "text":"Logic required to efficiently support sets of operations that do not stall"
                }
                , {
                  "type":"text"
                  , "text":"Logic required to efficiently support sets of operations that do not stall. This area cannot be affected directly."
                }
              ]
            }
            , {
              "name":"Computation"
              , "type":"resource"
              , "children":
              [
                {
                  "name":"No Source Line"
                  , "type":"resource"
                  , "data":
                  [34, 24, 0, 0, 0]
                  , "debug":
                  [
                    [
                      {
                        "filename":""
                        , "line":0
                      }
                    ]
                  ]
                  , "children":
                  [
                    {
                      "name":"Store"
                      , "type":"resource"
                      , "count":1
                      , "data":
                      [34, 24, 0, 0, 0]
                      , "details":
                      [
                        {
                          "type":"text"
                          , "text":"Store uses a Pipelined never-stall LSU"
                        }
                        , {
                          "type":"brief"
                          , "text":"Pipelined never-stall LSU"
                        }
                        , {
                          "type":"text"
                          , "text":"Stall-free write to memory declared on %L."
                          , "links":
                          [
                            {
                              "filename":"firmware/myproject.cpp"
                              , "line":"47"
                            }
                          ]
                        }
                      ]
                    }
                  ]
                }
                , {
                  "name":"myproject.cpp:46"
                  , "type":"resource"
                  , "data":
                  [1, 0, 0, 0, 0]
                  , "debug":
                  [
                    [
                      {
                        "filename":"/home/renz/hls4ml_14/firmware/myproject.cpp"
                        , "line":46
                      }
                    ]
                  ]
                  , "children":
                  [
                    {
                      "name":"Stream Read"
                      , "type":"resource"
                      , "count":1
                      , "data":
                      [1, 0, 0, 0, 0]
                    }
                  ]
                  , "replace_name":"true"
                }
              ]
            }
          ]
        }
        , {
          "name":"myproject.B2"
          , "type":"basicblock"
          , "children":
          [
            {
              "name":"State"
              , "type":"resource"
              , "data":
              [926, 1849, 0, 0, 0]
              , "details":
              [
                {
                  "type":"brief"
                  , "text":"Live values and control logic"
                }
                , {
                  "type":"text"
                  , "text":"Resources for live values and control logic. To reduce this area:"
                  , "details":
                  [
                    {
                      "type":"text"
                      , "text":"reduce size of local variables"
                    }
                    , {
                      "type":"text"
                      , "text":"reduce scope of local variables, localizing them as much as possible"
                    }
                    , {
                      "type":"text"
                      , "text":"reduce number of nested loops"
                    }
                  ]
                }
              ]
              , "children":
              [
                {
                  "name":"No Source Line"
                  , "type":"resource"
                  , "data":
                  [926, 1849, 0, 0, 0]
                }
              ]
            }
            , {
              "name":"Feedback"
              , "type":"resource"
              , "data":
              [4, 2, 1, 0, 0]
              , "details":
              [
                {
                  "type":"brief"
                  , "text":"Loop-carried dependencies"
                }
                , {
                  "type":"text"
                  , "text":"Resources for loop-carried dependencies. To reduce this area:"
                  , "details":
                  [
                    {
                      "type":"text"
                      , "text":"reduce number and size of loop-carried variables"
                    }
                  ]
                }
              ]
              , "children":
              [
                {
                  "name":"myproject.cpp:63 > nnet_dense.h:163 > \nnnet_dense.h:133 > ac_fixed.h:300"
                  , "type":"resource"
                  , "data":
                  [4, 2, 1, 0, 0]
                  , "debug":
                  [
                    [
                      {
                        "filename":"/home/renz/hls4ml_14/firmware/myproject.cpp"
                        , "line":63
                      }
                      , {
                        "filename":"/home/renz/hls4ml_14/firmware/nnet_utils/nnet_dense.h"
                        , "line":163
                      }
                      , {
                        "filename":"/home/renz/hls4ml_14/firmware/nnet_utils/nnet_dense.h"
                        , "line":133
                      }
                    ]
                  ]
                }
              ]
            }
            , {
              "name":"Computation"
              , "type":"resource"
              , "children":
              [
                {
                  "name":"myproject.cpp:66 > nnet_activation.h:41"
                  , "type":"resource"
                  , "data":
                  [248, 0, 0, 0, 0]
                  , "debug":
                  [
                    [
                      {
                        "filename":"/home/renz/hls4ml_14/firmware/myproject.cpp"
                        , "line":66
                      }
                      , {
                        "filename":"/home/renz/hls4ml_14/firmware/nnet_utils/nnet_activation.h"
                        , "line":41
                      }
                    ]
                  ]
                  , "children":
                  [
                    {
                      "name":"16-bit Select"
                      , "type":"resource"
                      , "count":31
                      , "data":
                      [248, 0, 0, 0, 0]
                    }
                  ]
                  , "replace_name":"true"
                }
                , {
                  "name":"myproject.cpp:66 > nnet_activation.h:41 > \nac_fixed.h:1601 > ac_fixed.h:1040 > \nac_int.h:905"
                  , "type":"resource"
                  , "data":
                  [1364, 31, 0, 0, 0]
                  , "debug":
                  [
                    [
                      {
                        "filename":"/home/renz/hls4ml_14/firmware/myproject.cpp"
                        , "line":66
                      }
                      , {
                        "filename":"/home/renz/hls4ml_14/firmware/nnet_utils/nnet_activation.h"
                        , "line":41
                      }
                    ]
                  ]
                  , "children":
                  [
                    {
                      "name":"41-bit Integer Compare"
                      , "type":"resource"
                      , "count":31
                      , "data":
                      [1364, 31, 0, 0, 0]
                    }
                  ]
                  , "replace_name":"true"
                }
              ]
            }
          ]
        }
        , {
          "name":"myproject.B3"
          , "type":"basicblock"
          , "children":
          [
            {
              "name":"Computation"
              , "type":"resource"
              , "children":
              [
                {
                  "name":"myproject.cpp:76"
                  , "type":"resource"
                  , "data":
                  [3, 2, 0, 0, 0]
                  , "debug":
                  [
                    [
                      {
                        "filename":"/home/renz/hls4ml_14/firmware/myproject.cpp"
                        , "line":76
                      }
                    ]
                  ]
                  , "children":
                  [
                    {
                      "name":"Stream Write"
                      , "type":"resource"
                      , "count":1
                      , "data":
                      [3, 2, 0, 0, 0]
                    }
                  ]
                  , "replace_name":"true"
                }
              ]
            }
          ]
        }
        , {
          "name":"myproject.B4"
          , "type":"basicblock"
          , "children":
          [
            {
              "name":"State"
              , "type":"resource"
              , "data":
              [211, 2124, 0, 0, 8]
              , "details":
              [
                {
                  "type":"brief"
                  , "text":"Live values and control logic"
                }
                , {
                  "type":"text"
                  , "text":"Resources for live values and control logic. To reduce this area:"
                  , "details":
                  [
                    {
                      "type":"text"
                      , "text":"reduce size of local variables"
                    }
                    , {
                      "type":"text"
                      , "text":"reduce scope of local variables, localizing them as much as possible"
                    }
                    , {
                      "type":"text"
                      , "text":"reduce number of nested loops"
                    }
                  ]
                }
              ]
              , "children":
              [
                {
                  "name":"No Source Line"
                  , "type":"resource"
                  , "data":
                  [211, 2124, 0, 0, 8]
                }
              ]
            }
            , {
              "name":"Feedback"
              , "type":"resource"
              , "data":
              [80, 1112, 0, 0, 0]
              , "details":
              [
                {
                  "type":"brief"
                  , "text":"Loop-carried dependencies"
                }
                , {
                  "type":"text"
                  , "text":"Resources for loop-carried dependencies. To reduce this area:"
                  , "details":
                  [
                    {
                      "type":"text"
                      , "text":"reduce number and size of loop-carried variables"
                    }
                  ]
                }
              ]
              , "children":
              [
                {
                  "name":"No Source Line"
                  , "type":"resource"
                  , "data":
                  [48, 1016, 0, 0, 0]
                }
                , {
                  "name":"myproject.cpp:63 > nnet_dense.h:163 > \nnnet_dense.h:141 > ac_fixed.h:800 > \nac_fixed.h:317 > ac_int.h:614"
                  , "type":"resource"
                  , "data":
                  [12, 88, 0, 0, 0]
                  , "debug":
                  [
                    [
                      {
                        "filename":"/home/renz/hls4ml_14/firmware/myproject.cpp"
                        , "line":63
                      }
                      , {
                        "filename":"/home/renz/hls4ml_14/firmware/nnet_utils/nnet_dense.h"
                        , "line":163
                      }
                      , {
                        "filename":"/home/renz/hls4ml_14/firmware/nnet_utils/nnet_dense.h"
                        , "line":141
                      }
                    ]
                  ]
                }
                , {
                  "name":"myproject.cpp:69 > nnet_dense.h:163 > \nnnet_dense.h:114"
                  , "type":"resource"
                  , "data":
                  [11, 0, 0, 0, 0]
                  , "debug":
                  [
                    [
                      {
                        "filename":"/home/renz/hls4ml_14/firmware/myproject.cpp"
                        , "line":69
                      }
                      , {
                        "filename":"/home/renz/hls4ml_14/firmware/nnet_utils/nnet_dense.h"
                        , "line":163
                      }
                      , {
                        "filename":"/home/renz/hls4ml_14/firmware/nnet_utils/nnet_dense.h"
                        , "line":114
                      }
                    ]
                  ]
                }
                , {
                  "name":"myproject.cpp:69 > nnet_dense.h:163 > \nnnet_dense.h:123"
                  , "type":"resource"
                  , "data":
                  [9, 8, 0, 0, 0]
                  , "debug":
                  [
                    [
                      {
                        "filename":"/home/renz/hls4ml_14/firmware/myproject.cpp"
                        , "line":69
                      }
                      , {
                        "filename":"/home/renz/hls4ml_14/firmware/nnet_utils/nnet_dense.h"
                        , "line":163
                      }
                      , {
                        "filename":"/home/renz/hls4ml_14/firmware/nnet_utils/nnet_dense.h"
                        , "line":123
                      }
                    ]
                  ]
                }
              ]
            }
            , {
              "name":"Cluster logic"
              , "type":"resource"
              , "data":
              [8, 6, 0, 0, 13]
              , "details":
              [
                {
                  "type":"brief"
                  , "text":"Logic required to efficiently support sets of operations that do not stall"
                }
                , {
                  "type":"text"
                  , "text":"Logic required to efficiently support sets of operations that do not stall. This area cannot be affected directly."
                }
              ]
            }
            , {
              "name":"Computation"
              , "type":"resource"
              , "children":
              [
                {
                  "name":"myproject.cpp:66 > nnet_activation.h:41"
                  , "type":"resource"
                  , "data":
                  [16, 16, 0, 0, 0]
                  , "debug":
                  [
                    [
                      {
                        "filename":"/home/renz/hls4ml_14/firmware/myproject.cpp"
                        , "line":66
                      }
                      , {
                        "filename":"/home/renz/hls4ml_14/firmware/nnet_utils/nnet_activation.h"
                        , "line":41
                      }
                    ]
                  ]
                  , "children":
                  [
                    {
                      "name":"16-bit Select"
                      , "type":"resource"
                      , "count":1
                      , "data":
                      [16, 16, 0, 0, 0]
                    }
                  ]
                  , "replace_name":"true"
                }
                , {
                  "name":"myproject.cpp:66 > nnet_activation.h:41 > \nac_fixed.h:1601 > ac_fixed.h:1040 > \nac_int.h:905"
                  , "type":"resource"
                  , "data":
                  [44, 1, 0, 0, 0]
                  , "debug":
                  [
                    [
                      {
                        "filename":"/home/renz/hls4ml_14/firmware/myproject.cpp"
                        , "line":66
                      }
                      , {
                        "filename":"/home/renz/hls4ml_14/firmware/nnet_utils/nnet_activation.h"
                        , "line":41
                      }
                    ]
                  ]
                  , "children":
                  [
                    {
                      "name":"41-bit Integer Compare"
                      , "type":"resource"
                      , "count":1
                      , "data":
                      [44, 1, 0, 0, 0]
                    }
                  ]
                  , "replace_name":"true"
                }
                , {
                  "name":"myproject.cpp:69 > nnet_dense.h:163 > \nnnet_dense.h:123"
                  , "type":"resource"
                  , "data":
                  [2, 0, 0, 0, 0]
                  , "debug":
                  [
                    [
                      {
                        "filename":"/home/renz/hls4ml_14/firmware/myproject.cpp"
                        , "line":69
                      }
                      , {
                        "filename":"/home/renz/hls4ml_14/firmware/nnet_utils/nnet_dense.h"
                        , "line":163
                      }
                      , {
                        "filename":"/home/renz/hls4ml_14/firmware/nnet_utils/nnet_dense.h"
                        , "line":123
                      }
                    ]
                  ]
                  , "children":
                  [
                    {
                      "name":"6-bit Integer Compare"
                      , "type":"resource"
                      , "count":1
                      , "data":
                      [2, 0, 0, 0, 0]
                    }
                  ]
                  , "replace_name":"true"
                }
                , {
                  "name":"myproject.cpp:69 > nnet_dense.h:163 > \nnnet_dense.h:133 > nnet_mult.h:65 > \nac_fixed.h:739 > ac_int.h:712"
                  , "type":"resource"
                  , "data":
                  [0, 0, 0, 5, 0]
                  , "debug":
                  [
                    [
                      {
                        "filename":"/home/renz/hls4ml_14/firmware/myproject.cpp"
                        , "line":69
                      }
                      , {
                        "filename":"/home/renz/hls4ml_14/firmware/nnet_utils/nnet_dense.h"
                        , "line":163
                      }
                      , {
                        "filename":"/home/renz/hls4ml_14/firmware/nnet_utils/nnet_dense.h"
                        , "line":133
                      }
                      , {
                        "filename":"/home/renz/hls4ml_14/firmware/nnet_utils/nnet_mult.h"
                        , "line":65
                      }
                    ]
                  ]
                  , "children":
                  [
                    {
                      "name":"signed 16-bit x signed 16-bit to 32-bit Integer Multiply"
                      , "type":"resource"
                      , "count":10
                      , "data":
                      [0, 0, 0, 5, 0]
                    }
                  ]
                  , "replace_name":"true"
                }
                , {
                  "name":"myproject.cpp:69 > nnet_dense.h:163 > \nnnet_dense.h:133 > ac_fixed.h:300"
                  , "type":"resource"
                  , "data":
                  [352, 80, 10, 0, 0]
                  , "debug":
                  [
                    [
                      {
                        "filename":"/home/renz/hls4ml_14/firmware/myproject.cpp"
                        , "line":69
                      }
                      , {
                        "filename":"/home/renz/hls4ml_14/firmware/nnet_utils/nnet_dense.h"
                        , "line":163
                      }
                      , {
                        "filename":"/home/renz/hls4ml_14/firmware/nnet_utils/nnet_dense.h"
                        , "line":133
                      }
                    ]
                  ]
                  , "children":
                  [
                    {
                      "name":"On-chip Read-Only Memory Lookup"
                      , "type":"resource"
                      , "count":10
                      , "data":
                      [0, 0, 10, 0, 0]
                      , "details":
                      [
                        {
                          "type":"brief"
                          , "text":"Read from 5120 bit ROM. "
                        }
                        , {
                          "type":"text"
                          , "text":"Read from 5120 bit ROM. A copy of the ROM is created for each access."
                        }
                      ]
                    }
                    , {
                      "name":"llvm.fpga.case"
                      , "type":"resource"
                      , "count":5
                      , "data":
                      [352, 80, 0, 0, 0]
                    }
                  ]
                  , "replace_name":"true"
                }
                , {
                  "name":"myproject.cpp:69 > nnet_dense.h:163 > \nnnet_dense.h:141 > ac_fixed.h:800 > \nac_fixed.h:749 > ac_int.h:719"
                  , "type":"resource"
                  , "data":
                  [240, 0, 0, 0, 0]
                  , "debug":
                  [
                    [
                      {
                        "filename":"/home/renz/hls4ml_14/firmware/myproject.cpp"
                        , "line":69
                      }
                      , {
                        "filename":"/home/renz/hls4ml_14/firmware/nnet_utils/nnet_dense.h"
                        , "line":163
                      }
                      , {
                        "filename":"/home/renz/hls4ml_14/firmware/nnet_utils/nnet_dense.h"
                        , "line":141
                      }
                    ]
                  ]
                  , "children":
                  [
                    {
                      "name":"24-bit Integer Add"
                      , "type":"resource"
                      , "count":10
                      , "data":
                      [240, 0, 0, 0, 0]
                    }
                  ]
                  , "replace_name":"true"
                }
              ]
            }
          ]
        }
        , {
          "name":"myproject.B5"
          , "type":"basicblock"
          , "children":
          [
            {
              "name":"State"
              , "type":"resource"
              , "data":
              [12, 3334, 0, 0, 0]
              , "details":
              [
                {
                  "type":"brief"
                  , "text":"Live values and control logic"
                }
                , {
                  "type":"text"
                  , "text":"Resources for live values and control logic. To reduce this area:"
                  , "details":
                  [
                    {
                      "type":"text"
                      , "text":"reduce size of local variables"
                    }
                    , {
                      "type":"text"
                      , "text":"reduce scope of local variables, localizing them as much as possible"
                    }
                    , {
                      "type":"text"
                      , "text":"reduce number of nested loops"
                    }
                  ]
                }
              ]
              , "children":
              [
                {
                  "name":"No Source Line"
                  , "type":"resource"
                  , "data":
                  [12, 3334, 0, 0, 0]
                }
              ]
            }
            , {
              "name":"Feedback"
              , "type":"resource"
              , "data":
              [394, 4296, 0, 0, 0]
              , "details":
              [
                {
                  "type":"brief"
                  , "text":"Loop-carried dependencies"
                }
                , {
                  "type":"text"
                  , "text":"Resources for loop-carried dependencies. To reduce this area:"
                  , "details":
                  [
                    {
                      "type":"text"
                      , "text":"reduce number and size of loop-carried variables"
                    }
                  ]
                }
              ]
              , "children":
              [
                {
                  "name":"myproject.cpp:63 > nnet_dense.h:163 > \nnnet_dense.h:114"
                  , "type":"resource"
                  , "data":
                  [33, 0, 0, 0, 0]
                  , "debug":
                  [
                    [
                      {
                        "filename":"/home/renz/hls4ml_14/firmware/myproject.cpp"
                        , "line":63
                      }
                      , {
                        "filename":"/home/renz/hls4ml_14/firmware/nnet_utils/nnet_dense.h"
                        , "line":163
                      }
                      , {
                        "filename":"/home/renz/hls4ml_14/firmware/nnet_utils/nnet_dense.h"
                        , "line":114
                      }
                    ]
                  ]
                }
                , {
                  "name":"myproject.cpp:63 > nnet_dense.h:163 > \nnnet_dense.h:123"
                  , "type":"resource"
                  , "data":
                  [9, 8, 0, 0, 0]
                  , "debug":
                  [
                    [
                      {
                        "filename":"/home/renz/hls4ml_14/firmware/myproject.cpp"
                        , "line":63
                      }
                      , {
                        "filename":"/home/renz/hls4ml_14/firmware/nnet_utils/nnet_dense.h"
                        , "line":163
                      }
                      , {
                        "filename":"/home/renz/hls4ml_14/firmware/nnet_utils/nnet_dense.h"
                        , "line":123
                      }
                    ]
                  ]
                }
                , {
                  "name":"myproject.cpp:63 > nnet_dense.h:163 > \nnnet_dense.h:141 > ac_fixed.h:800"
                  , "type":"resource"
                  , "data":
                  [352, 4288, 0, 0, 0]
                  , "debug":
                  [
                    [
                      {
                        "filename":"/home/renz/hls4ml_14/firmware/myproject.cpp"
                        , "line":63
                      }
                      , {
                        "filename":"/home/renz/hls4ml_14/firmware/nnet_utils/nnet_dense.h"
                        , "line":163
                      }
                      , {
                        "filename":"/home/renz/hls4ml_14/firmware/nnet_utils/nnet_dense.h"
                        , "line":141
                      }
                    ]
                  ]
                }
              ]
            }
            , {
              "name":"Cluster logic"
              , "type":"resource"
              , "data":
              [8, 6, 0, 0, 66]
              , "details":
              [
                {
                  "type":"brief"
                  , "text":"Logic required to efficiently support sets of operations that do not stall"
                }
                , {
                  "type":"text"
                  , "text":"Logic required to efficiently support sets of operations that do not stall. This area cannot be affected directly."
                }
              ]
            }
            , {
              "name":"Computation"
              , "type":"resource"
              , "children":
              [
                {
                  "name":"myproject.cpp:63 > nnet_dense.h:163 > \nnnet_dense.h:123"
                  , "type":"resource"
                  , "data":
                  [3, 0, 0, 0, 0]
                  , "debug":
                  [
                    [
                      {
                        "filename":"/home/renz/hls4ml_14/firmware/myproject.cpp"
                        , "line":63
                      }
                      , {
                        "filename":"/home/renz/hls4ml_14/firmware/nnet_utils/nnet_dense.h"
                        , "line":163
                      }
                      , {
                        "filename":"/home/renz/hls4ml_14/firmware/nnet_utils/nnet_dense.h"
                        , "line":123
                      }
                    ]
                  ]
                  , "children":
                  [
                    {
                      "name":"9-bit Integer Compare"
                      , "type":"resource"
                      , "count":1
                      , "data":
                      [3, 0, 0, 0, 0]
                    }
                  ]
                  , "replace_name":"true"
                }
                , {
                  "name":"myproject.cpp:63 > nnet_dense.h:163 > \nnnet_dense.h:133 > nnet_mult.h:65 > \nac_fixed.h:739 > ac_int.h:710"
                  , "type":"resource"
                  , "data":
                  [328, 0, 0, 4, 0]
                  , "debug":
                  [
                    [
                      {
                        "filename":"/home/renz/hls4ml_14/firmware/myproject.cpp"
                        , "line":63
                      }
                      , {
                        "filename":"/home/renz/hls4ml_14/firmware/nnet_utils/nnet_dense.h"
                        , "line":163
                      }
                      , {
                        "filename":"/home/renz/hls4ml_14/firmware/nnet_utils/nnet_dense.h"
                        , "line":133
                      }
                      , {
                        "filename":"/home/renz/hls4ml_14/firmware/nnet_utils/nnet_mult.h"
                        , "line":65
                      }
                    ]
                  ]
                  , "children":
                  [
                    {
                      "name":"16bit Integer Dot Product of Size 1"
                      , "type":"resource"
                      , "count":32
                      , "data":
                      [0, 0, 0, 4, 0]
                    }
                    , {
                      "name":"41-bit Integer Add"
                      , "type":"resource"
                      , "count":32
                      , "data":
                      [328, 0, 0, 0, 0]
                    }
                  ]
                  , "replace_name":"true"
                }
                , {
                  "name":"myproject.cpp:63 > nnet_dense.h:163 > \nnnet_dense.h:133 > nnet_mult.h:65 > \nac_fixed.h:739 > ac_int.h:711"
                  , "type":"resource"
                  , "data":
                  [328, 0, 0, 4, 0]
                  , "debug":
                  [
                    [
                      {
                        "filename":"/home/renz/hls4ml_14/firmware/myproject.cpp"
                        , "line":63
                      }
                      , {
                        "filename":"/home/renz/hls4ml_14/firmware/nnet_utils/nnet_dense.h"
                        , "line":163
                      }
                      , {
                        "filename":"/home/renz/hls4ml_14/firmware/nnet_utils/nnet_dense.h"
                        , "line":133
                      }
                      , {
                        "filename":"/home/renz/hls4ml_14/firmware/nnet_utils/nnet_mult.h"
                        , "line":65
                      }
                    ]
                  ]
                  , "children":
                  [
                    {
                      "name":"16bit Integer Dot Product of Size 1"
                      , "type":"resource"
                      , "count":32
                      , "data":
                      [0, 0, 0, 4, 0]
                    }
                    , {
                      "name":"41-bit Integer Add"
                      , "type":"resource"
                      , "count":32
                      , "data":
                      [328, 0, 0, 0, 0]
                    }
                  ]
                  , "replace_name":"true"
                }
                , {
                  "name":"myproject.cpp:63 > nnet_dense.h:163 > \nnnet_dense.h:133 > nnet_mult.h:65 > \nac_fixed.h:739 > ac_int.h:712"
                  , "type":"resource"
                  , "data":
                  [328, 0, 0, 4, 0]
                  , "debug":
                  [
                    [
                      {
                        "filename":"/home/renz/hls4ml_14/firmware/myproject.cpp"
                        , "line":63
                      }
                      , {
                        "filename":"/home/renz/hls4ml_14/firmware/nnet_utils/nnet_dense.h"
                        , "line":163
                      }
                      , {
                        "filename":"/home/renz/hls4ml_14/firmware/nnet_utils/nnet_dense.h"
                        , "line":133
                      }
                      , {
                        "filename":"/home/renz/hls4ml_14/firmware/nnet_utils/nnet_mult.h"
                        , "line":65
                      }
                    ]
                  ]
                  , "children":
                  [
                    {
                      "name":"16bit Integer Dot Product of Size 1"
                      , "type":"resource"
                      , "count":32
                      , "data":
                      [0, 0, 0, 4, 0]
                    }
                    , {
                      "name":"41-bit Integer Add"
                      , "type":"resource"
                      , "count":32
                      , "data":
                      [328, 0, 0, 0, 0]
                    }
                  ]
                  , "replace_name":"true"
                }
                , {
                  "name":"myproject.cpp:63 > nnet_dense.h:163 > \nnnet_dense.h:133 > ac_fixed.h:300"
                  , "type":"resource"
                  , "data":
                  [594, 825, 0, 0, 0]
                  , "debug":
                  [
                    [
                      {
                        "filename":"/home/renz/hls4ml_14/firmware/myproject.cpp"
                        , "line":63
                      }
                      , {
                        "filename":"/home/renz/hls4ml_14/firmware/nnet_utils/nnet_dense.h"
                        , "line":163
                      }
                      , {
                        "filename":"/home/renz/hls4ml_14/firmware/nnet_utils/nnet_dense.h"
                        , "line":133
                      }
                    ]
                  ]
                  , "children":
                  [
                    {
                      "name":"Load"
                      , "type":"resource"
                      , "count":33
                      , "data":
                      [594, 825, 0, 0, 0]
                      , "details":
                      [
                        {
                          "type":"text"
                          , "text":"Load uses a Pipelined never-stall LSU"
                        }
                        , {
                          "type":"brief"
                          , "text":"Pipelined never-stall LSU"
                        }
                        , {
                          "type":"text"
                          , "text":"Stall-free read from memory declared on %L."
                          , "links":
                          [
                            {
                              "filename":"firmware/weights/w3.h"
                              , "line":"15"
                            }
                          ]
                        }
                      ]
                    }
                  ]
                  , "replace_name":"true"
                }
                , {
                  "name":"myproject.cpp:63 > nnet_dense.h:163 > \nnnet_dense.h:141 > ac_fixed.h:800 > \nac_fixed.h:317 > ac_int.h:614"
                  , "type":"resource"
                  , "data":
                  [328, 0, 0, 4, 0]
                  , "debug":
                  [
                    [
                      {
                        "filename":"/home/renz/hls4ml_14/firmware/myproject.cpp"
                        , "line":63
                      }
                      , {
                        "filename":"/home/renz/hls4ml_14/firmware/nnet_utils/nnet_dense.h"
                        , "line":163
                      }
                      , {
                        "filename":"/home/renz/hls4ml_14/firmware/nnet_utils/nnet_dense.h"
                        , "line":141
                      }
                    ]
                  ]
                  , "children":
                  [
                    {
                      "name":"16bit Integer Dot Product of Size 1"
                      , "type":"resource"
                      , "count":32
                      , "data":
                      [0, 0, 0, 4, 0]
                    }
                    , {
                      "name":"41-bit Integer Add"
                      , "type":"resource"
                      , "count":32
                      , "data":
                      [328, 0, 0, 0, 0]
                    }
                  ]
                  , "replace_name":"true"
                }
              ]
            }
          ]
        }
      ]
    }
  ]
}
